{
    "osa":{
        "icd9-cm":["327.20","327.23","327.29","780.51","780.53","780.57"],
        "icd10-cm":["G47.30","G47.33","G47.39"],
        "meta":{
            "full":"obstructive sleep apnea"
        }
    },
    "mi":{
        "icd9-cm":["410","412"],
        "icd10-cm":["I21", "I22", "I25.2"],
        "meta":{
            "full":"myocardial infarction"
        }
    },
    "st":{
        "icd9-cm":["431","434"],
        "icd10-cm":["I61","I62","I63","I64"],
        "meta":{
            "full":"stroke"
        }
    },
    "chf":{
        "icd9-cm":["428"],
        "icd10-cm":["I50"],
        "meta":{
            "full":"congestive heart failure"
        }
    },
    "cardpx":{
        "icd9-cm":["360","361"],
        "icd10-pcs":["021","027"],
        "hcpcs":[
            "92973","92974","92975","92980","92981","92982","92984","92995","92996",
            "92920", "92921", "92922", "92923", "92924", "92925", "92926", "92927", 
            "92928", "92929", "92930", "92931", "92932", "92933", "92934", "92935", 
            "92936", "92937", "92938", "92939", "92940", "92941", "92942", "92943"
        ],
        "meta":{
            "full":"cardiac procedures"
        }
    },
    "peripx":{
        "icd9-cm":["004","006.6"],
        "hcpcs":[
            "37220", "37221", "37222", "37223", "37224", "37225", "37226", "37227", "37228", 
            "37229", "37230", "37231", "37232", "37233", "37234","37215", "37216", "37217",
            "37218", "37211", "37212", "37213","37184", "37185", "37186", "37187", "37236", 
            "37237", "37238", "37239", "37240", "37241", "37242", "37243", "37244", "37245", 
            "37246", "37247", "37248"
       ],
       "meta":{
        "full":"peripheral procedures"
       }
    },
    "obes":{
        "icd9-cm":["278.00", "278.01", "278.03"],
        "icd10-cm":["E66","Z68.3","Z68.4"],
        "meta":{
            "full":"obesity"
        }
    },
    "t2dm":{
        "icd9-cm":["250","357.2","362.0"],
        "icd10-cm":["E08","E09","E10","E11","E12","E13"],
        "meta":{
            "full":"type 2 diabetes mellitus"
        }
    },
    "htn":{
        "icd9-cm":["401","402","403","404","405"],
        "icd10-cm":["I10","I11","I12","I13","R03"],
        "meta":{
            "full":"hypertension"
        }
    },
    "afib":{
        "icd9-cm":["4273"],
        "icd10-cm":["I48"],
        "meta":{
            "full":"atrial fibrillation"
        }
    },
    "cbv":{
        "icd9-cm":[
            "436","435.9","438.1","438.2","438.3","438.4","438.5","438.8","438.9",
            "434.91","434.11","434.01","433.01","433.11","433.21","433.91","433.81","V12.54"
        ],
        "icd10-cm":["I60","I61","I62","I63","I64","I65","I66","I67"],
        "meta":{
            "full":"cerebrovascular disease"
        }
    },
    "hysm":{
        "icd9-cm":["327.1","307.43","307.44","780.54"],
        "icd10-cm":["F51.1","G47.1"],
        "meta":{
            "full":"hypersomnia"
        }
    },
    "insm":{
        "icd9-cm":["327.0","307.41","307.42","780.52"],
        "icd10-cm":["G47.0","F51.01","F51.02","F51.09"],
        "meta":{
            "full":"insomina"
        }
    },
    "copd":{
        "icd9-cm":["496"],
        "icd10-cm":["J44"],
        "meta":{
            "full":"chronic obstructive pulmonary disease"
        }
    },
    "bsx":{
        "icd9-cm":[
            "438.2","438.9","443.1","443.2","443.8","443.9","445","446.8",
            "446.9","449.5","449.6","449.7","449.8","449.9","459","459.1"],
        "icd10-pcs":[
            "0DB64Z3","0DV64CZ","0D16479","0D1647A","0D1647B","0D1647L","0D164J9","0D164JA","0D164JB","0D164JL",
            "0D164K9","0D164KA","0D164KB","0D164KL","0D164Z9","0D164ZA","0D164ZB","0D164ZL","0D16079","0D1607A",
            "0D1607B","0D1607L","0D160J9","0D160JA","0D160JB","0D160JL","0D160K9","0D160KA","0D160KB","0D160KL",
            "0D160Z9","0D160ZA","0D160ZB","0D160ZL","0D16879","0D1687A","0D1687B","0D1687L","0D168J9","0D168JA",
            "0D168JB","0D168JL","0D168K9","0D168KA","0D168KB","0D168KL","0D168Z9","0D168ZA","0D168ZB","0D168ZL"],
        "hcpcs":[
            "43290","43291","43620","43621","43622","43631","43632","43633","43634","43644","43645",
            "43770", "43771", "43772", "43773", "43774","43842", "43843", "43844", "43845", "43846",
            "43886","43887","43888","43860","43865"
        ],
        "meta":{
            "full":"bariatric surgery"
        }
    },
    "nd":{
        "icd9-cm":["300"],
        "icd10-cm":["F40","F41","F42","F43","F44","F45","F46","F47","F48"],
        "meta":{
            "full":"neurotic disorders"
        }
    },
    "arf":{
        "icd9-cm":["584","586"],
        "icd10-cm":["N17"],
        "meta":{
            "full":"acute renal failure"
        }
    },
    "ckd":{
        "icd9-cm":["585"],
        "icd10-cm":["N18"],
        "meta":{
            "full":"chronic kidney disease"
        }
    },
    "esrd":{
        "icd9-cm":["585.6"],
        "icd10-cm":["N18.6"],
        "meta":{
            "full":"end stage renal disease"
        }
    }
}